Workbook

Sheet Financials
A1: ticker | B1: year | C1: revenue | D1: gross_profit | E1: operating_income | F1: net_income | G1: cost_of_goods_sold | H1: total_assets | I1: current_assets | J1: current_liabilities | K1: total_liabilities | L1: equity | M1: consolidated_equity | N1: cash | O1: inventory | P1: accounts_receivable | Q1: operating_cash_flow | R1: capital_expenditure | S1: interest_expense | T1: net_interest_and_other
A2: KO | B2: 2022 | C2: 43004000000 | D2: 25004000000 | E2: 10909000000 | F2: 9542000000 | G2: 18000000000 | H2: 92763000000 | I2: 22591000000 | J2: 19724000000 | K2: 66937000000 | L2: 24105000000 | M2: 25826000000 | N2: 9519000000 | O2: 4233000000 | P2: 3487000000 | Q2: 11018000000 | R2: 1484000000 | S2: 882000000
A3: KO | B3: 2023 | C3: 45754000000 | D3: 27234000000 | E3: 11311000000 | F3: 10714000000 | G3: 18520000000 | H3: 97703000000 | I3: 26732000000 | J3: 23571000000 | K3: 70223000000 | L3: 25941000000 | M3: 27480000000 | N3: 9366000000 | O3: 4424000000 | P3: 3410000000 | Q3: 11599000000 | R3: 1852000000 | S3: 1527000000
A4: KO | B4: 2024 | C4: 47061000000 | D4: 28737000000 | E4: 9992000000 | F4: 10631000000 | G4: 18324000000 | H4: 100549000000 | I4: 25997000000 | J4: 25249000000 | K4: 74177000000 | L4: 24856000000 | M4: 26372000000 | N4: 10828000000 | O4: 4728000000 | P4: 3569000000 | Q4: 6805000000 | R4: 2064000000 | S4: 1656000000
A5: PEP | B5: 2022 | C5: 86392000000 | D5: 45816000000 | E5: 11512000000 | F5: 8910000000 | G5: 40576000000 | H5: 92187000000 | I5: 21539000000 | J5: 26785000000 | K5: 74914000000 | L5: 17149000000 | M5: 17273000000 | N5: 4954000000 | O5: 5222000000 | P5: 10163000000 | Q5: 10811000000 | R5: 5207000000 | T5: 939000000
A6: PEP | B6: 2023 | C6: 91471000000 | D6: 49590000000 | E6: 11986000000 | F6: 9074000000 | G6: 41881000000 | H6: 100495000000 | I6: 26950000000 | J6: 31647000000 | K6: 81858000000 | L6: 18503000000 | M6: 18637000000 | N6: 9711000000 | O6: 5334000000 | P6: 10815000000 | Q6: 13442000000 | R6: 5518000000 | T6: 819000000
A7: PEP | B7: 2024 | C7: 91854000000 | D7: 50110000000 | E7: 12887000000 | F7: 9578000000 | G7: 41744000000 | H7: 99467000000 | I7: 25826000000 | J7: 31536000000 | K7: 81296000000 | L7: 18041000000 | M7: 18171000000 | N7: 8505000000 | O7: 5306000000 | P7: 10333000000 | Q7: 12507000000 | R7: 5318000000 | T7: 919000000
A8: KDP | B8: 2022 | C8: 14057000000 | D8: 7323000000 | E8: 2605000000 | F8: 1436000000 | G8: 6734000000 | H8: 51837000000 | I8: 3804000000 | J8: 8076000000 | K8: 26712000000 | L8: 25126000000 | M8: 25125000000 | N8: 535000000 | O8: 1314000000 | P8: 1484000000 | Q8: 2837000000 | R8: 353000000 | S8: 693000000
A9: KDP | B9: 2023 | C9: 14814000000 | D9: 8080000000 | E9: 3192000000 | F9: 2181000000 | G9: 6734000000 | H9: 52130000000 | I9: 3375000000 | J9: 8916000000 | K9: 26454000000 | L9: 25676000000 | M9: 25676000000 | N9: 267000000 | O9: 1142000000 | P9: 1368000000 | Q9: 1329000000 | R9: 425000000 | S9: 496000000
A10: KDP | B10: 2024 | C10: 15351000000 | D10: 8529000000 | E10: 2591000000 | F10: 1441000000 | G10: 6822000000 | H10: 53430000000 | I10: 3997000000 | J10: 8087000000 | K10: 29187000000 | L10: 24243000000 | M10: 24243000000 | N10: 510000000 | O10: 1299000000 | P10: 1502000000 | Q10: 2219000000 | R10: 563000000

Sheet Ratios
A1: ticker | B1: year | C1: operating_margin | D1: current_ratio | E1: liabilities_to_assets | F1: cfo_margin | G1: fcf_margin
A2: =Financials!A2 | B2: =Financials!B2 | C2: =IF(AND(ISNUMBER(Financials!E2),ISNUMBER(Financials!C2),Financials!C2>0),Financials!E2/Financials!C2,"") | D2: =IF(AND(ISNUMBER(Financials!I2),ISNUMBER(Financials!J2),Financials!J2>0),Financials!I2/Financials!J2,"") | E2: =IF(AND(ISNUMBER(Financials!K2),ISNUMBER(Financials!H2),Financials!H2>0),Financials!K2/Financials!H2,"") | F2: =IF(AND(ISNUMBER(Financials!Q2),ISNUMBER(Financials!C2),Financials!C2>0),Financials!Q2/Financials!C2,"") | G2: =IF(AND(ISNUMBER(Financials!Q2),ISNUMBER(Financials!C2),ISNUMBER(Financials!R2),Financials!C2>0),(Financials!Q2-Financials!R2)/Financials!C2,"")
A3: =Financials!A3 | B3: =Financials!B3 | C3: =IF(AND(ISNUMBER(Financials!E3),ISNUMBER(Financials!C3),Financials!C3>0),Financials!E3/Financials!C3,"") | D3: =IF(AND(ISNUMBER(Financials!I3),ISNUMBER(Financials!J3),Financials!J3>0),Financials!I3/Financials!J3,"") | E3: =IF(AND(ISNUMBER(Financials!K3),ISNUMBER(Financials!H3),Financials!H3>0),Financials!K3/Financials!H3,"") | F3: =IF(AND(ISNUMBER(Financials!Q3),ISNUMBER(Financials!C3),Financials!C3>0),Financials!Q3/Financials!C3,"") | G3: =IF(AND(ISNUMBER(Financials!Q3),ISNUMBER(Financials!C3),ISNUMBER(Financials!R3),Financials!C3>0),(Financials!Q3-Financials!R3)/Financials!C3,"")
A4: =Financials!A4 | B4: =Financials!B4 | C4: =IF(AND(ISNUMBER(Financials!E4),ISNUMBER(Financials!C4),Financials!C4>0),Financials!E4/Financials!C4,"") | D4: =IF(AND(ISNUMBER(Financials!I4),ISNUMBER(Financials!J4),Financials!J4>0),Financials!I4/Financials!J4,"") | E4: =IF(AND(ISNUMBER(Financials!K4),ISNUMBER(Financials!H4),Financials!H4>0),Financials!K4/Financials!H4,"") | F4: =IF(AND(ISNUMBER(Financials!Q4),ISNUMBER(Financials!C4),Financials!C4>0),Financials!Q4/Financials!C4,"") | G4: =IF(AND(ISNUMBER(Financials!Q4),ISNUMBER(Financials!C4),ISNUMBER(Financials!R4),Financials!C4>0),(Financials!Q4-Financials!R4)/Financials!C4,"")
A5: =Financials!A5 | B5: =Financials!B5 | C5: =IF(AND(ISNUMBER(Financials!E5),ISNUMBER(Financials!C5),Financials!C5>0),Financials!E5/Financials!C5,"") | D5: =IF(AND(ISNUMBER(Financials!I5),ISNUMBER(Financials!J5),Financials!J5>0),Financials!I5/Financials!J5,"") | E5: =IF(AND(ISNUMBER(Financials!K5),ISNUMBER(Financials!H5),Financials!H5>0),Financials!K5/Financials!H5,"") | F5: =IF(AND(ISNUMBER(Financials!Q5),ISNUMBER(Financials!C5),Financials!C5>0),Financials!Q5/Financials!C5,"") | G5: =IF(AND(ISNUMBER(Financials!Q5),ISNUMBER(Financials!C5),ISNUMBER(Financials!R5),Financials!C5>0),(Financials!Q5-Financials!R5)/Financials!C5,"")
A6: =Financials!A6 | B6: =Financials!B6 | C6: =IF(AND(ISNUMBER(Financials!E6),ISNUMBER(Financials!C6),Financials!C6>0),Financials!E6/Financials!C6,"") | D6: =IF(AND(ISNUMBER(Financials!I6),ISNUMBER(Financials!J6),Financials!J6>0),Financials!I6/Financials!J6,"") | E6: =IF(AND(ISNUMBER(Financials!K6),ISNUMBER(Financials!H6),Financials!H6>0),Financials!K6/Financials!H6,"") | F6: =IF(AND(ISNUMBER(Financials!Q6),ISNUMBER(Financials!C6),Financials!C6>0),Financials!Q6/Financials!C6,"") | G6: =IF(AND(ISNUMBER(Financials!Q6),ISNUMBER(Financials!C6),ISNUMBER(Financials!R6),Financials!C6>0),(Financials!Q6-Financials!R6)/Financials!C6,"")
A7: =Financials!A7 | B7: =Financials!B7 | C7: =IF(AND(ISNUMBER(Financials!E7),ISNUMBER(Financials!C7),Financials!C7>0),Financials!E7/Financials!C7,"") | D7: =IF(AND(ISNUMBER(Financials!I7),ISNUMBER(Financials!J7),Financials!J7>0),Financials!I7/Financials!J7,"") | E7: =IF(AND(ISNUMBER(Financials!K7),ISNUMBER(Financials!H7),Financials!H7>0),Financials!K7/Financials!H7,"") | F7: =IF(AND(ISNUMBER(Financials!Q7),ISNUMBER(Financials!C7),Financials!C7>0),Financials!Q7/Financials!C7,"") | G7: =IF(AND(ISNUMBER(Financials!Q7),ISNUMBER(Financials!C7),ISNUMBER(Financials!R7),Financials!C7>0),(Financials!Q7-Financials!R7)/Financials!C7,"")
A8: =Financials!A8 | B8: =Financials!B8 | C8: =IF(AND(ISNUMBER(Financials!E8),ISNUMBER(Financials!C8),Financials!C8>0),Financials!E8/Financials!C8,"") | D8: =IF(AND(ISNUMBER(Financials!I8),ISNUMBER(Financials!J8),Financials!J8>0),Financials!I8/Financials!J8,"") | E8: =IF(AND(ISNUMBER(Financials!K8),ISNUMBER(Financials!H8),Financials!H8>0),Financials!K8/Financials!H8,"") | F8: =IF(AND(ISNUMBER(Financials!Q8),ISNUMBER(Financials!C8),Financials!C8>0),Financials!Q8/Financials!C8,"") | G8: =IF(AND(ISNUMBER(Financials!Q8),ISNUMBER(Financials!C8),ISNUMBER(Financials!R8),Financials!C8>0),(Financials!Q8-Financials!R8)/Financials!C8,"")
A9: =Financials!A9 | B9: =Financials!B9 | C9: =IF(AND(ISNUMBER(Financials!E9),ISNUMBER(Financials!C9),Financials!C9>0),Financials!E9/Financials!C9,"") | D9: =IF(AND(ISNUMBER(Financials!I9),ISNUMBER(Financials!J9),Financials!J9>0),Financials!I9/Financials!J9,"") | E9: =IF(AND(ISNUMBER(Financials!K9),ISNUMBER(Financials!H9),Financials!H9>0),Financials!K9/Financials!H9,"") | F9: =IF(AND(ISNUMBER(Financials!Q9),ISNUMBER(Financials!C9),Financials!C9>0),Financials!Q9/Financials!C9,"") | G9: =IF(AND(ISNUMBER(Financials!Q9),ISNUMBER(Financials!C9),ISNUMBER(Financials!R9),Financials!C9>0),(Financials!Q9-Financials!R9)/Financials!C9,"")
A10: =Financials!A10 | B10: =Financials!B10 | C10: =IF(AND(ISNUMBER(Financials!E10),ISNUMBER(Financials!C10),Financials!C10>0),Financials!E10/Financials!C10,"") | D10: =IF(AND(ISNUMBER(Financials!I10),ISNUMBER(Financials!J10),Financials!J10>0),Financials!I10/Financials!J10,"") | E10: =IF(AND(ISNUMBER(Financials!K10),ISNUMBER(Financials!H10),Financials!H10>0),Financials!K10/Financials!H10,"") | F10: =IF(AND(ISNUMBER(Financials!Q10),ISNUMBER(Financials!C10),Financials!C10>0),Financials!Q10/Financials!C10,"") | G10: =IF(AND(ISNUMBER(Financials!Q10),ISNUMBER(Financials!C10),ISNUMBER(Financials!R10),Financials!C10>0),(Financials!Q10-Financials!R10)/Financials!C10,"")

Sheet Evidence
A1: ticker | B1: year | C1: field | D1: kind | E1: concept_or_formula | F1: accession | G1: filed | H1: source_sha256
A2: KO | B2: 2022 | C2: revenue | D2: reported | E2: Revenues | F2: 0000021344-23-000011 | G2: 2023-02-21 | H2: 53d363a9aa3071406cda9857654358f4dca42e174a1defb8cc1ce9ad2a4c9e40
A3: KO | B3: 2022 | C3: gross_profit | D3: reported | E3: GrossProfit | F3: 0000021344-23-000011 | G3: 2023-02-21 | H3: 53d363a9aa3071406cda9857654358f4dca42e174a1defb8cc1ce9ad2a4c9e40
A4: KO | B4: 2022 | C4: operating_income | D4: reported | E4: OperatingIncomeLoss | F4: 0000021344-23-000011 | G4: 2023-02-21 | H4: 53d363a9aa3071406cda9857654358f4dca42e174a1defb8cc1ce9ad2a4c9e40
A5: KO | B5: 2022 | C5: net_income | D5: reported | E5: NetIncomeLoss | F5: 0000021344-23-000011 | G5: 2023-02-21 | H5: 53d363a9aa3071406cda9857654358f4dca42e174a1defb8cc1ce9ad2a4c9e40
A6: KO | B6: 2022 | C6: cost_of_goods_sold | D6: reported | E6: CostOfGoodsAndServicesSold | F6: 0000021344-23-000011 | G6: 2023-02-21 | H6: 53d363a9aa3071406cda9857654358f4dca42e174a1defb8cc1ce9ad2a4c9e40
A7: KO | B7: 2022 | C7: total_assets | D7: reported | E7: Assets | F7: 0000021344-23-000011 | G7: 2023-02-21 | H7: 53d363a9aa3071406cda9857654358f4dca42e174a1defb8cc1ce9ad2a4c9e40
A8: KO | B8: 2022 | C8: current_assets | D8: reported | E8: AssetsCurrent | F8: 0000021344-23-000011 | G8: 2023-02-21 | H8: 53d363a9aa3071406cda9857654358f4dca42e174a1defb8cc1ce9ad2a4c9e40
A9: KO | B9: 2022 | C9: current_liabilities | D9: reported | E9: LiabilitiesCurrent | F9: 0000021344-23-000011 | G9: 2023-02-21 | H9: 53d363a9aa3071406cda9857654358f4dca42e174a1defb8cc1ce9ad2a4c9e40
A10: KO | B10: 2022 | C10: total_liabilities | D10: derived | E10: total_assets - consolidated_equity
A11: KO | B11: 2022 | C11: equity | D11: reported | E11: StockholdersEquity | F11: 0000021344-23-000011 | G11: 2023-02-21 | H11: 53d363a9aa3071406cda9857654358f4dca42e174a1defb8cc1ce9ad2a4c9e40
A12: KO | B12: 2022 | C12: consolidated_equity | D12: reported | E12: StockholdersEquityIncludingPortionAttributableToNoncontrollingInterest | F12: 0000021344-23-000011 | G12: 2023-02-21 | H12: 53d363a9aa3071406cda9857654358f4dca42e174a1defb8cc1ce9ad2a4c9e40
A13: KO | B13: 2022 | C13: cash | D13: reported | E13: CashAndCashEquivalentsAtCarryingValue | F13: 0000021344-23-000011 | G13: 2023-02-21 | H13: 53d363a9aa3071406cda9857654358f4dca42e174a1defb8cc1ce9ad2a4c9e40
A14: KO | B14: 2022 | C14: inventory | D14: reported | E14: InventoryNet | F14: 0000021344-23-000011 | G14: 2023-02-21 | H14: 53d363a9aa3071406cda9857654358f4dca42e174a1defb8cc1ce9ad2a4c9e40
A15: KO | B15: 2022 | C15: accounts_receivable | D15: reported | E15: AccountsReceivableNetCurrent | F15: 0000021344-23-000011 | G15: 2023-02-21 | H15: 53d363a9aa3071406cda9857654358f4dca42e174a1defb8cc1ce9ad2a4c9e40
A16: KO | B16: 2022 | C16: operating_cash_flow | D16: reported | E16: NetCashProvidedByUsedInOperatingActivities | F16: 0000021344-23-000011 | G16: 2023-02-21 | H16: 53d363a9aa3071406cda9857654358f4dca42e174a1defb8cc1ce9ad2a4c9e40
A17: KO | B17: 2022 | C17: capital_expenditure | D17: reported | E17: PaymentsToAcquirePropertyPlantAndEquipment | F17: 0000021344-23-000011 | G17: 2023-02-21 | H17: 53d363a9aa3071406cda9857654358f4dca42e174a1defb8cc1ce9ad2a4c9e40
A18: KO | B18: 2022 | C18: interest_expense | D18: reported | E18: InterestExpense | F18: 0000021344-23-000011 | G18: 2023-02-21 | H18: 53d363a9aa3071406cda9857654358f4dca42e174a1defb8cc1ce9ad2a4c9e40
A19: KO | B19: 2023 | C19: revenue | D19: reported | E19: Revenues | F19: 0000021344-24-000009 | G19: 2024-02-20 | H19: 53d363a9aa3071406cda9857654358f4dca42e174a1defb8cc1ce9ad2a4c9e40
A20: KO | B20: 2023 | C20: gross_profit | D20: reported | E20: GrossProfit | F20: 0000021344-24-000009 | G20: 2024-02-20 | H20: 53d363a9aa3071406cda9857654358f4dca42e174a1defb8cc1ce9ad2a4c9e40
A21: KO | B21: 2023 | C21: operating_income | D21: reported | E21: OperatingIncomeLoss | F21: 0000021344-24-000009 | G21: 2024-02-20 | H21: 53d363a9aa3071406cda9857654358f4dca42e174a1defb8cc1ce9ad2a4c9e40
A22: KO | B22: 2023 | C22: net_income | D22: reported | E22: NetIncomeLoss | F22: 0000021344-24-000009 | G22: 2024-02-20 | H22: 53d363a9aa3071406cda9857654358f4dca42e174a1defb8cc1ce9ad2a4c9e40
... A26: KO | B26: 2023 | C26: current_liabilities | D26: reported | E26: LiabilitiesCurrent | F26: 0000021344-24-000009 | G26: 2024-02-20 | H26: 53d363a9aa3071406cda9857654358f4dca42e174a1defb8cc1ce9ad2a4c9e40
A27: KO | B27: 2023 | C27: total_liabilities | D27: derived | E27: total_assets - consolidated_equity
A28: KO | B28: 2023 | C28: equity | D28: reported | E28: StockholdersEquity | F28: 0000021344-24-000009 | G28: 2024-02-20 | H28: 53d363a9aa3071406cda9857654358f4dca42e174a1defb8cc1ce9ad2a4c9e40
A29: KO | B29: 2023 | C29: consolidated_equity | D29: reported | E29: StockholdersEquityIncludingPortionAttributableToNoncontrollingInterest | F29: 0000021344-24-000009 | G29: 2024-02-20 | H29: 53d363a9aa3071406cda9857654358f4dca42e174a1defb8cc1ce9ad2a4c9e40
A30: KO | B30: 2023 | C30: cash | D30: reported | E30: CashAndCashEquivalentsAtCarryingValue | F30: 0000021344-24-000009 | G30: 2024-02-20 | H30: 53d363a9aa3071406cda9857654358f4dca42e174a1defb8cc1ce9ad2a4c9e40
A31: KO | B31: 2023 | C31: inventory | D31: reported | E31: InventoryNet | F31: 0000021344-24-000009 | G31: 2024-02-20 | H31: 53d363a9aa3071406cda9857654358f4dca42e174a1defb8cc1ce9ad2a4c9e40
A32: KO | B32: 2023 | C32: accounts_receivable | D32: reported | E32: AccountsReceivableNetCurrent | F32: 0000021344-24-000009 | G32: 2024-02-20 | H32: 53d363a9aa3071406cda9857654358f4dca42e174a1defb8cc1ce9ad2a4c9e40
A33: KO | B33: 2023 | C33: operating_cash_flow | D33: reported | E33: NetCashProvidedByUsedInOperatingActivities | F33: 0000021344-24-000009 | G33: 2024-02-20 | H33: 53d363a9aa3071406cda9857654358f4dca42e174a1defb8cc1ce9ad2a4c9e40
A34: KO | B34: 2023 | C34: capital_expenditure | D34: reported | E34: PaymentsToAcquirePropertyPlantAndEquipment | F34: 0000021344-24-000009 | G34: 2024-02-20 | H34: 53d363a9aa3071406cda9857654358f4dca42e174a1defb8cc1ce9ad2a4c9e40
A35: KO | B35: 2023 | C35: interest_expense | D35: reported | E35: InterestExpense | F35: 0000021344-24-000009 | G35: 2024-02-20 | H35: 53d363a9aa3071406cda9857654358f4dca42e174a1defb8cc1ce9ad2a4c9e40
A36: KO | B36: 2024 | C36: revenue | D36: reported | E36: Revenues | F36: 0000021344-25-000011 | G36: 2025-02-20 | H36: 53d363a9aa3071406cda9857654358f4dca42e174a1defb8cc1ce9ad2a4c9e40
A37: KO | B37: 2024 | C37: gross_profit | D37: reported | E37: GrossProfit | F37: 0000021344-25-000011 | G37: 2025-02-20 | H37: 53d363a9aa3071406cda9857654358f4dca42e174a1defb8cc1ce9ad2a4c9e40
A38: KO | B38: 2024 | C38: operating_income | D38: reported | E38: OperatingIncomeLoss | F38: 0000021344-25-000011 | G38: 2025-02-20 | H38: 53d363a9aa3071406cda9857654358f4dca42e174a1defb8cc1ce9ad2a4c9e40
A39: KO | B39: 2024 | C39: net_income | D39: reported | E39: NetIncomeLoss | F39: 0000021344-25-000011 | G39: 2025-02-20 | H39: 53d363a9aa3071406cda9857654358f4dca42e174a1defb8cc1ce9ad2a4c9e40
... A43: KO | B43: 2024 | C43: current_liabilities | D43: reported | E43: LiabilitiesCurrent | F43: 0000021344-25-000011 | G43: 2025-02-20 | H43: 53d363a9aa3071406cda9857654358f4dca42e174a1defb8cc1ce9ad2a4c9e40
A44: KO | B44: 2024 | C44: total_liabilities | D44: derived | E44: total_assets - consolidated_equity
A45: KO | B45: 2024 | C45: equity | D45: reported | E45: StockholdersEquity | F45: 0000021344-25-000011 | G45: 2025-02-20 | H45: 53d363a9aa3071406cda9857654358f4dca42e174a1defb8cc1ce9ad2a4c9e40
A46: KO | B46: 2024 | C46: consolidated_equity | D46: reported | E46: StockholdersEquityIncludingPortionAttributableToNoncontrollingInterest | F46: 0000021344-25-000011 | G46: 2025-02-20 | H46: 53d363a9aa3071406cda9857654358f4dca42e174a1defb8cc1ce9ad2a4c9e40
A47: KO | B47: 2024 | C47: cash | D47: reported | E47: CashAndCashEquivalentsAtCarryingValue | F47: 0000021344-25-000011 | G47: 2025-02-20 | H47: 53d363a9aa3071406cda9857654358f4dca42e174a1defb8cc1ce9ad2a4c9e40
A48: KO | B48: 2024 | C48: inventory | D48: reported | E48: InventoryNet | F48: 0000021344-25-000011 | G48: 2025-02-20 | H48: 53d363a9aa3071406cda9857654358f4dca42e174a1defb8cc1ce9ad2a4c9e40
A49: KO | B49: 2024 | C49: accounts_receivable | D49: reported | E49: AccountsReceivableNetCurrent | F49: 0000021344-25-000011 | G49: 2025-02-20 | H49: 53d363a9aa3071406cda9857654358f4dca42e174a1defb8cc1ce9ad2a4c9e40
A50: KO | B50: 2024 | C50: operating_cash_flow | D50: reported | E50: NetCashProvidedByUsedInOperatingActivities | F50: 0000021344-25-000011 | G50: 2025-02-20 | H50: 53d363a9aa3071406cda9857654358f4dca42e174a1defb8cc1ce9ad2a4c9e40
A51: KO | B51: 2024 | C51: capital_expenditure | D51: reported | E51: PaymentsToAcquirePropertyPlantAndEquipment | F51: 0000021344-25-000011 | G51: 2025-02-20 | H51: 53d363a9aa3071406cda9857654358f4dca42e174a1defb8cc1ce9ad2a4c9e40
A52: KO | B52: 2024 | C52: interest_expense | D52: reported | E52: InterestExpense | F52: 0000021344-25-000011 | G52: 2025-02-20 | H52: 53d363a9aa3071406cda9857654358f4dca42e174a1defb8cc1ce9ad2a4c9e40
A53: PEP | B53: 2022 | C53: revenue | D53: reported | E53: Revenues | F53: 0000077476-23-000007 | G53: 2023-02-09 | H53: 7694c322779ef273d15b3791729e5f2d261ce6ed1839be8ff014a33f537375be
A54: PEP | B54: 2022 | C54: gross_profit | D54: reported | E54: GrossProfit | F54: 0000077476-23-000007 | G54: 2023-02-09 | H54: 7694c322779ef273d15b3791729e5f2d261ce6ed1839be8ff014a33f537375be
A55: PEP | B55: 2022 | C55: operating_income | D55: reported | E55: OperatingIncomeLoss | F55: 0000077476-23-000007 | G55: 2023-02-09 | H55: 7694c322779ef273d15b3791729e5f2d261ce6ed1839be8ff014a33f537375be
A56: PEP | B56: 2022 | C56: net_income | D56: reported | E56: NetIncomeLoss | F56: 0000077476-23-000007 | G56: 2023-02-09 | H56: 7694c322779ef273d15b3791729e5f2d261ce6ed1839be8ff014a33f537375be
... A68: PEP | B68: 2022 | C68: capital_expenditure | D68: reported | E68: PaymentsToAcquireProductiveAssets | F68: 0000077476-23-000007 | G68: 2023-02-09 | H68: 7694c322779ef273d15b3791729e5f2d261ce6ed1839be8ff014a33f537375be
A69: PEP | B69: 2022 | C69: interest_expense | D69: unavailable | E69: The issuer's InterestExpense fact represents net interest expense and other. It is preserved separately as net_interest_and_other; gross interest expense is not sourced here.
A70: PEP | B70: 2022 | C70: net_interest_and_other | D70: reported | E70: InterestExpense | F70: 0000077476-23-000007 | G70: 2023-02-09 | H70: 7694c322779ef273d15b3791729e5f2d261ce6ed1839be8ff014a33f537375be
A71: PEP | B71: 2023 | C71: revenue | D71: reported | E71: Revenues | F71: 0000077476-24-000008 | G71: 2024-02-09 | H71: 7694c322779ef273d15b3791729e5f2d261ce6ed1839be8ff014a33f537375be
A72: PEP | B72: 2023 | C72: gross_profit | D72: reported | E72: GrossProfit | F72: 0000077476-24-000008 | G72: 2024-02-09 | H72: 7694c322779ef273d15b3791729e5f2d261ce6ed1839be8ff014a33f537375be
A73: PEP | B73: 2023 | C73: operating_income | D73: reported | E73: OperatingIncomeLoss | F73: 0000077476-24-000008 | G73: 2024-02-09 | H73: 7694c322779ef273d15b3791729e5f2d261ce6ed1839be8ff014a33f537375be
A74: PEP | B74: 2023 | C74: net_income | D74: reported | E74: NetIncomeLoss | F74: 0000077476-24-000008 | G74: 2024-02-09 | H74: 7694c322779ef273d15b3791729e5f2d261ce6ed1839be8ff014a33f537375be
A75: PEP | B75: 2023 | C75: cost_of_goods_sold | D75: reported | E75: CostOfGoodsAndServicesSold | F75: 0000077476-24-000008 | G75: 2024-02-09 | H75: 7694c322779ef273d15b3791729e5f2d261ce6ed1839be8ff014a33f537375be
A76: PEP | B76: 2023 | C76: total_assets | D76: reported | E76: Assets | F76: 0000077476-24-000008 | G76: 2024-02-09 | H76: 7694c322779ef273d15b3791729e5f2d261ce6ed1839be8ff014a33f537375be
A77: PEP | B77: 2023 | C77: current_assets | D77: reported | E77: AssetsCurrent | F77: 0000077476-24-000008 | G77: 2024-02-09 | H77: 7694c322779ef273d15b3791729e5f2d261ce6ed1839be8ff014a33f537375be
A78: PEP | B78: 2023 | C78: current_liabilities | D78: reported | E78: LiabilitiesCurrent | F78: 0000077476-24-000008 | G78: 2024-02-09 | H78: 7694c322779ef273d15b3791729e5f2d261ce6ed1839be8ff014a33f537375be
A79: PEP | B79: 2023 | C79: total_liabilities | D79: reported | E79: Liabilities | F79: 0000077476-24-000008 | G79: 2024-02-09 | H79: 7694c322779ef273d15b3791729e5f2d261ce6ed1839be8ff014a33f537375be
A80: PEP | B80: 2023 | C80: equity | D80: reported | E80: StockholdersEquity | F80: 0000077476-24-000008 | G80: 2024-02-09 | H80: 7694c322779ef273d15b3791729e5f2d261ce6ed1839be8ff014a33f537375be
A81: PEP | B81: 2023 | C81: consolidated_equity | D81: reported | E81: StockholdersEquityIncludingPortionAttributableToNoncontrollingInterest | F81: 0000077476-24-000008 | G81: 2024-02-09 | H81: 7694c322779ef273d15b3791729e5f2d261ce6ed1839be8ff014a33f537375be
... A86: PEP | B86: 2023 | C86: capital_expenditure | D86: reported | E86: PaymentsToAcquireProductiveAssets | F86: 0000077476-24-000008 | G86: 2024-02-09 | H86: 7694c322779ef273d15b3791729e5f2d261ce6ed1839be8ff014a33f537375be
A87: PEP | B87: 2023 | C87: interest_expense | D87: unavailable | E87: The issuer's InterestExpense fact represents net interest expense and other. It is preserved separately as net_interest_and_other; gross interest expense is not sourced here.
A88: PEP | B88: 2023 | C88: net_interest_and_other | D88: reported | E88: InterestExpense | F88: 0000077476-24-000008 | G88: 2024-02-09 | H88: 7694c322779ef273d15b3791729e5f2d261ce6ed1839be8ff014a33f537375be
A89: PEP | B89: 2024 | C89: revenue | D89: reported | E89: Revenues | F89: 0000077476-25-000007 | G89: 2025-02-04 | H89: 7694c322779ef273d15b3791729e5f2d261ce6ed1839be8ff014a33f537375be
A90: PEP | B90: 2024 | C90: gross_profit | D90: reported | E90: GrossProfit | F90: 0000077476-25-000007 | G90: 2025-02-04 | H90: 7694c322779ef273d15b3791729e5f2d261ce6ed1839be8ff014a33f537375be
A91: PEP | B91: 2024 | C91: operating_income | D91: reported | E91: OperatingIncomeLoss | F91: 0000077476-25-000007 | G91: 2025-02-04 | H91: 7694c322779ef273d15b3791729e5f2d261ce6ed1839be8ff014a33f537375be
A92: PEP | B92: 2024 | C92: net_income | D92: reported | E92: NetIncomeLoss | F92: 0000077476-25-000007 | G92: 2025-02-04 | H92: 7694c322779ef273d15b3791729e5f2d261ce6ed1839be8ff014a33f537375be
A93: PEP | B93: 2024 | C93: cost_of_goods_sold | D93: reported | E93: CostOfGoodsAndServicesSold | F93: 0000077476-25-000007 | G93: 2025-02-04 | H93: 7694c322779ef273d15b3791729e5f2d261ce6ed1839be8ff014a33f537375be
A94: PEP | B94: 2024 | C94: total_assets | D94: reported | E94: Assets | F94: 0000077476-25-000007 | G94: 2025-02-04 | H94: 7694c322779ef273d15b3791729e5f2d261ce6ed1839be8ff014a33f537375be
A95: PEP | B95: 2024 | C95: current_assets | D95: reported | E95: AssetsCurrent | F95: 0000077476-25-000007 | G95: 2025-02-04 | H95: 7694c322779ef273d15b3791729e5f2d261ce6ed1839be8ff014a33f537375be
A96: PEP | B96: 2024 | C96: current_liabilities | D96: reported | E96: LiabilitiesCurrent | F96: 0000077476-25-000007 | G96: 2025-02-04 | H96: 7694c322779ef273d15b3791729e5f2d261ce6ed1839be8ff014a33f537375be
A97: PEP | B97: 2024 | C97: total_liabilities | D97: reported | E97: Liabilities | F97: 0000077476-25-000007 | G97: 2025-02-04 | H97: 7694c322779ef273d15b3791729e5f2d261ce6ed1839be8ff014a33f537375be
A98: PEP | B98: 2024 | C98: equity | D98: reported | E98: StockholdersEquity | F98: 0000077476-25-000007 | G98: 2025-02-04 | H98: 7694c322779ef273d15b3791729e5f2d261ce6ed1839be8ff014a33f537375be
A99: PEP | B99: 2024 | C99: consolidated_equity | D99: reported | E99: StockholdersEquityIncludingPortionAttributableToNoncontrollingInterest | F99: 0000077476-25-000007 | G99: 2025-02-04 | H99: 7694c322779ef273d15b3791729e5f2d261ce6ed1839be8ff014a33f537375be
... A104: PEP | B104: 2024 | C104: capital_expenditure | D104: reported | E104: PaymentsToAcquireProductiveAssets | F104: 0000077476-25-000007 | G104: 2025-02-04 | H104: 7694c322779ef273d15b3791729e5f2d261ce6ed1839be8ff014a33f537375be
A105: PEP | B105: 2024 | C105: interest_expense | D105: unavailable | E105: The issuer's InterestExpense fact represents net interest expense and other. It is preserved separately as net_interest_and_other; gross interest expense is not sourced here.
A106: PEP | B106: 2024 | C106: net_interest_and_other | D106: reported | E106: InterestExpense | F106: 0000077476-25-000007 | G106: 2025-02-04 | H106: 7694c322779ef273d15b3791729e5f2d261ce6ed1839be8ff014a33f537375be
A107: KDP | B107: 2022 | C107: revenue | D107: reported | E107: RevenueFromContractWithCustomerExcludingAssessedTax | F107: 0001418135-23-000003 | G107: 2023-02-23 | H107: ada095aed6af778d3862b9fdfb75376ff216af33de7a7bf7f78f2b0fdd4d4416
A108: KDP | B108: 2022 | C108: gross_profit | D108: reported | E108: GrossProfit | F108: 0001418135-23-000003 | G108: 2023-02-23 | H108: ada095aed6af778d3862b9fdfb75376ff216af33de7a7bf7f78f2b0fdd4d4416
A109: KDP | B109: 2022 | C109: operating_income | D109: reported | E109: OperatingIncomeLoss | F109: 0001418135-23-000003 | G109: 2023-02-23 | H109: ada095aed6af778d3862b9fdfb75376ff216af33de7a7bf7f78f2b0fdd4d4416
A110: KDP | B110: 2022 | C110: net_income | D110: reported | E110: NetIncomeLoss | F110: 0001418135-23-000003 | G110: 2023-02-23 | H110: ada095aed6af778d3862b9fdfb75376ff216af33de7a7bf7f78f2b0fdd4d4416
A111: KDP | B111: 2022 | C111: cost_of_goods_sold | D111: reported | E111: CostOfGoodsAndServicesSold | F111: 0001418135-23-000003 | G111: 2023-02-23 | H111: ada095aed6af778d3862b9fdfb75376ff216af33de7a7bf7f78f2b0fdd4d4416
A112: KDP | B112: 2022 | C112: total_assets | D112: reported | E112: Assets | F112: 0001418135-23-000003 | G112: 2023-02-23 | H112: ada095aed6af778d3862b9fdfb75376ff216af33de7a7bf7f78f2b0fdd4d4416
A113: KDP | B113: 2022 | C113: current_assets | D113: reported | E113: AssetsCurrent | F113: 0001418135-23-000003 | G113: 2023-02-23 | H113: ada095aed6af778d3862b9fdfb75376ff216af33de7a7bf7f78f2b0fdd4d4416
A114: KDP | B114: 2022 | C114: current_liabilities | D114: reported | E114: LiabilitiesCurrent | F114: 0001418135-23-000003 | G114: 2023-02-23 | H114: ada095aed6af778d3862b9fdfb75376ff216af33de7a7bf7f78f2b0fdd4d4416
A115: KDP | B115: 2022 | C115: total_liabilities | D115: reported | E115: Liabilities | F115: 0001418135-23-000003 | G115: 2023-02-23 | H115: ada095aed6af778d3862b9fdfb75376ff216af33de7a7bf7f78f2b0fdd4d4416
A116: KDP | B116: 2022 | C116: equity | D116: reported | E116: StockholdersEquity | F116: 0001418135-23-000003 | G116: 2023-02-23 | H116: ada095aed6af778d3862b9fdfb75376ff216af33de7a7bf7f78f2b0fdd4d4416
A117: KDP | B117: 2022 | C117: consolidated_equity | D117: reported | E117: StockholdersEquityIncludingPortionAttributableToNoncontrollingInterest | F117: 0001418135-23-000003 | G117: 2023-02-23 | H117: ada095aed6af778d3862b9fdfb75376ff216af33de7a7bf7f78f2b0fdd4d4416
... A156: KDP | B156: 2024 | C156: capital_expenditure | D156: reported | E156: PaymentsToAcquirePropertyPlantAndEquipment | F156: 0001418135-25-000013 | G156: 2025-02-25 | H156: ada095aed6af778d3862b9fdfb75376ff216af33de7a7bf7f78f2b0fdd4d4416
A157: KDP | B157: 2024 | C157: interest_expense | D157: unavailable | E157: No matching standard-taxonomy USD fact in the selected filing; never filled with zero.

Sheet Read me
A1: Public filings credit review: beverages
A2: Information cutoff: 2025-04-01; all financials USD, ratios are fractions
A3: Earliest 10-K annual revenue accession for each period ending 2022–2024, filed by cutoff; exact accession, USD unit and start/end for other facts. Later amendments and restatements are excluded.
A4: Three US-listed corporations; no Asia, financial institution or fund case is evidenced here.
A5: Small selected peer set, including a foods business and differing fiscal calendars; medians are not sector benchmarks.
A6: Research screens and narrative are generated analysis. No agency rating, calibrated PD, lending limit, trade, client exposure or onboarding approval is claimed.
A7: Standard US-GAAP facts only. Missing concepts remain unavailable. Liabilities may be derived using equity including noncontrolling interests.
A8: FCF is defined here as operating cash flow less cash capital expenditure; it may differ from issuer non-GAAP measures. No one-off adjustments are applied.
A9: Annual historical monitoring only; current news, legal agreements, collateral and counterparty limits are outside this dataset.
A10: A cash ratio below one or a screening alert is not proof of default or a credit recommendation.
